Workbook

Sheet Supuestos
A1: Lo que se supone para sacar el neto
A3: Comisión que cobran las plataformas | B3: 0.3
A4: Dato de Javi, cerrado el 22 sep 2026 en 30%. No es la tarifa publicada. Airbnb declara 20% en Experiencias, pero sobre esa comisión corre el IVA del 16% —que la deja en 23.2%— y encima van conversión de divisa y proceso de pago. Las demás plataformas hacen lo mismo. Cambia esta celda y toda la hoja Netos se recalcula.
A9: Qué es el neto de esta hoja
A10: Lo que le queda al operador después de la comisión de la plataforma. Es el mismo número que le puede dar a Sincrético: no le pedimos mejor precio que a las OTAs, le pedimos el mismo. Nosotros además lo repartimos con quien lo vende.
A15: De dónde salen los precios
A16: Captura de listados públicos del 15 de septiembre de 2026, en crm_guias y crm_guia_tours. 455 anuncios de 393 tours de 235 guías. Todo en pesos mexicanos.
A20: Moneda
A21: TODAS las cifras de este archivo están en PESOS MEXICANOS (MXN). Donde aparezca un importe en dólares se escribe USD de forma explícita. Los contratos de las plataformas sí usan dólares en algunos umbrales —Viator retiene liquidaciones por debajo de USD 50, Airbnb cobra un mínimo de USD 6 en Servicios—; esos son dólares, no pesos, y no se han convertido.

Sheet Netos
A1: Guía | B1: Tour | C1: Zona | D1: Plataforma | E1: Rating | F1: Reseñas | G1: PVP público (MXN) | H1: Neto para nosotros (MXN) | I1: Web | J1: Instagram | K1: Correo | L1: WhatsApp | M1: Liga del anuncio
A2: A Chef's Tour | B2: Tour gastronómico por la Ciudad de México con 12+ degustaciones | C2: Centro Histórico | D2: Viator | E2: 4.8 | F2: 6 | G2: 1558 | H2: =IF(G2="","",ROUND(G2*(1-Supuestos!$B$3),0)) -> 1091 | I2: https://achefstour.com/ | J2: @achefstour | K2: info@achefstour.com | M2: https://www.viator.com/es-MX/tours/Mexico-City/x/d628-69673P126
A3: Abril · Find Mexico | B3: Tour privado a pie por el centro de la Ciudad de México | C3: Centro Histórico | D3: Viator | F3: 0 | G3: 350 | H3: =IF(G3="","",ROUND(G3*(1-Supuestos!$B$3),0)) -> 245 | M3: https://www.viator.com/es-MX/tours/Mexico-City/x/d628-5517516P1
A4: Adrenaline | B4: Tepito Tour Mercados locales, comida callejera y Santa Muerte | C4: Centro Histórico | D4: Viator | F4: 0 | G4: 1715 | H4: =IF(G4="","",ROUND(G4*(1-Supuestos!$B$3),0)) -> 1201 | M4: https://www.viator.com/es-MX/tours/Mexico-City/x/d628-91751P313
A5: Ady — Experience Mexico from the center: Legend and hi | B5: Experience Mexico from the center: Legend and history | C5: Centro Histórico | D5: Airbnb Experiences | E5: 5 | F5: 1 | G5: 758 | H5: =IF(G5="","",ROUND(G5*(1-Supuestos!$B$3),0)) -> 531 | M5: https://www.airbnb.com/experiences/6461639
A6: Alejandro Torres Rivera | B6: Ride a bike and cable car through Chapultepec | C6: Bici · varias colonias | D6: Airbnb Experiences | E6: 5 | F6: 4 | G6: 1480 | H6: =IF(G6="","",ROUND(G6*(1-Supuestos!$B$3),0)) -> 1036 | M6: https://www.airbnb.com/experiences/4763785
A7: ALEMEX TOURS | B7: Ciudad de México: recorrido guiado por la ciudad desde el Parque Chapultepec hasta la avenida Paseo de la Reforma | C7: Reforma/Juárez | D7: Airbnb Experiences | F7: 0 | G7: 703 | H7: =IF(G7="","",ROUND(G7*(1-Supuestos!$B$3),0)) -> 492 | I7: https://www.alemex-tours.com/ | L7: 491792001731 | M7: https://www.airbnb.com/experiences/6941466
A8: ALEMEX TOURS | B8: Ciudad de México: recorrido guiado por la ciudad desde el Parque Chapultepec hasta la avenida Paseo de la Reforma | C8: Reforma/Juárez | D8: GetYourGuide | E8: 5 | F8: 10 | G8: 630 | H8: =IF(G8="","",ROUND(G8*(1-Supuestos!$B$3),0)) -> 441 | I8: https://www.alemex-tours.com/ | L8: 491792001731 | M8: https://www.getyourguide.com/es-mx/ciudad-de-mexico-l194/-t1108573/
A9: ALEMEX TOURS | B9: Ciudad de México: Recorrido histórico por el centro – De los aztecas a la metrópoli | C9: Centro Histórico | D9: GetYourGuide | E9: 5 | F9: 6 | G9: 675 | H9: =IF(G9="","",ROUND(G9*(1-Supuestos!$B$3),0)) -> 472 | I9: https://www.alemex-tours.com/ | L9: 491792001731 | M9: https://www.getyourguide.com/es-mx/ciudad-de-mexico-l194/-t1141787/
A10: ALEMEX TOURS | B10: Ciudad de México: Recorrido histórico por el centro – De los aztecas a la metrópoli | C10: Centro Histórico | D10: Airbnb Experiences | E10: 5 | F10: 2 | G10: 814 | H10: =IF(G10="","",ROUND(G10*(1-Supuestos!$B$3),0)) -> 570 | I10: https://www.alemex-tours.com/ | L10: 491792001731 | M10: https://www.airbnb.com/experiences/6913997
A11: ALEMEX TOURS | B11: Ciudad de México: Recorrido histórico por el centro – De los aztecas a la metrópoli | C11: Centro Histórico | D11: Viator | F11: 0 | G11: 850 | H11: =IF(G11="","",ROUND(G11*(1-Supuestos!$B$3),0)) -> 595 | I11: https://www.alemex-tours.com/ | L11: 491792001731 | M11: https://www.viator.com/es-MX/tours/Mexico-City/x/d628-5652165P2
A12: ALEMEX TOURS | B12: From the Park to the Boulevard: Chapultepec & Reforma | C12: Reforma/Juárez | D12: Airbnb Experiences | F12: 0 | G12: 703 | H12: =IF(G12="","",ROUND(G12*(1-Supuestos!$B$3),0)) -> 492 | I12: https://www.alemex-tours.com/ | L12: 491792001731 | M12: https://www.airbnb.com/experiences/6955761
A13: ALEMEX TOURS | B13: Historic Center: From the Aztecs to the Present | C13: Centro Histórico | D13: Airbnb Experiences | E13: 5 | F13: 2 | G13: 814 | H13: =IF(G13="","",ROUND(G13*(1-Supuestos!$B$3),0)) -> 570 | I13: https://www.alemex-tours.com/ | L13: 491792001731 | M13: https://www.airbnb.com/experiences/6928261
A14: Alisa — Meet the ghosts of Mexico City | B14: Meet the ghosts of Mexico City | C14: Centro Histórico | D14: Airbnb Experiences | E14: 4.93 | F14: 509 | G14: 814 | H14: =IF(G14="","",ROUND(G14*(1-Supuestos!$B$3),0)) -> 570 | M14: https://www.airbnb.com/experiences/3111741
A15: ALOHA CDMX | B15: Noche de Barrio Tacos Mezcal y Música | C15: Centro Histórico | D15: Viator | F15: 0 | G15: 2600 | H15: =IF(G15="","",ROUND(G15*(1-Supuestos!$B$3),0)) -> 1820 | M15: https://www.viator.com/es-MX/tours/Mexico-City/x/d628-427760P4
A16: Amazing photoshoot in downtown Mexico City | B16: Explorando el centro de la Ciudad de México a través de la lente | C16: Centro Histórico | D16: Viator | F16: 0 | G16: 2000 | H16: =IF(G16="","",ROUND(G16*(1-Supuestos!$B$3),0)) -> 1400 | M16: https://www.viator.com/es-MX/tours/Mexico-City/x/d628-5599437P2
A17: Amigo Tours | B17: Ciudad de México: tour nocturno a pie con opción de Torre Latino | C17: Centro Histórico | D17: GetYourGuide | E17: 3.65 | F17: 42 | G17: 617.39 | H17: =IF(G17="","",ROUND(G17*(1-Supuestos!$B$3),0)) -> 432 | I17: https://amigotours.com/ | J17: @amigo.tours | K17: cdmx@amigotours.com | L17: 525545638246 | M17: https://www.getyourguide.com/es-mx/ciudad-de-mexico-l194/-t409964/
A18: Amigo Tours | B18: Ciudad de México: tour nocturno a pie con opción de Torre Latino | C18: Centro Histórico | D18: Viator | E18: 4.3 | F18: 48 | G18: 630 | H18: =IF(G18="","",ROUND(G18*(1-Supuestos!$B$3),0)) -> 441 | I18: https://amigotours.com/ | J18: @amigo.tours | K18: cdmx@amigotours.com | L18: 525545638246 | M18: https://www.viator.com/es-MX/tours/Mexico-City/x/d628-5885P196
A19: Amigo Tours | B19: Ciudad de México: tour privado en bicicleta por el Bosque de Chapultepec | C19: Reforma/Juárez | D19: Viator | E19: 4.7 | F19: 24 | G19: 2118 | H19: =IF(G19="","",ROUND(G19*(1-Supuestos!$B$3),0)) -> 1483 | I19: https://amigotours.com/ | J19: @amigo.tours | K19: cdmx@amigotours.com | L19: 525545638246 | M19: https://www.viator.com/es-MX/tours/Mexico-City/x/d628-5885P432
A20: Amigo Tours | B20: Ciudad de México: tour privado en bicicleta por el Bosque de Chapultepec | C20: Reforma/Juárez | D20: GetYourGuide | E20: 4.78 | F20: 16 | G20: 2418.09 | H20: =IF(G20="","",ROUND(G20*(1-Supuestos!$B$3),0)) -> 1693 | I20: https://amigotours.com/ | J20: @amigo.tours | K20: cdmx@amigotours.com | L20: 525545638246 | M20: https://www.getyourguide.com/es-mx/ciudad-de-mexico-l194/-t434289/
A21: Amigo Tours | B21: Day of the Dead Tour | C21: Centro Histórico | D21: Airbnb Experiences | F21: 0 | G21: 1517 | H21: =IF(G21="","",ROUND(G21*(1-Supuestos!$B$3),0)) -> 1062 | I21: https://amigotours.com/ | J21: @amigo.tours | K21: cdmx@amigotours.com | L21: 525545638246 | M21: https://www.airbnb.com/experiences/6951617
A22: Amigo Tours | B22: Edificios y palacios imperdibles de la Ciudad de México | C22: Centro Histórico | D22: GetYourGuide | E22: 4.36 | F22: 36 | G22: 823.18 | H22: =IF(G22="","",ROUND(G22*(1-Supuestos!$B$3),0)) -> 576 | I22: https://amigotours.com/ | J22: @amigo.tours | K22: cdmx@amigotours.com | L22: 525545638246 | M22: https://www.getyourguide.com/es-mx/ciudad-de-mexico-l194/-t433804/
A23: Amigo Tours | B23: Tour de Mercados Locales & Comida Exótica | C23: Centro Histórico | D23: Airbnb Experiences | E23: 4.5 | F23: 2 | G23: 1073 | H23: =IF(G23="","",ROUND(G23*(1-Supuestos!$B$3),0)) -> 751 | I23: https://amigotours.com/ | J23: @amigo.tours | K23: cdmx@amigotours.com | L23: 525545638246 | M23: https://www.airbnb.com/experiences/6952959
A24: Amigo Tours | B24: Tour de Mercados Locales & Comida Exótica | C24: Centro Histórico | D24: Viator | E24: 4.3 | F24: 23 | G24: 1103 | H24: =IF(G24="","",ROUND(G24*(1-Supuestos!$B$3),0)) -> 772 | I24: https://amigotours.com/ | J24: @amigo.tours | K24: cdmx@amigotours.com | L24: 525545638246 | M24: https://www.viator.com/es-MX/tours/Mexico-City/x/d628-5885P431
A25: Amigo Tours | B25: Tour por el Banco Nacional y los palacios de Ciudad de Mexico | C25: Centro Histórico | D25: Civitatis | E25: 4.65 | F25: 3 | G25: 4562 | H25: =IF(G25="","",ROUND(G25*(1-Supuestos!$B$3),0)) -> 3193 | I25: https://amigotours.com/ | J25: @amigo.tours | K25: cdmx@amigotours.com | L25: 525545638246 | M25: https://www.civitatis.com/es/ciudad-de-mexico/banco-nacional-palacios-ciudad-mexico/
A26: Ancient Tenochtitlán Tours | B26: Tour Ciudad de México Antigua : Degustación de Cacao & Historia Azteca en CDMX | C26: Centro Histórico | D26: Viator | E26: 4 | F26: 1 | G26: 1558 | H26: =IF(G26="","",ROUND(G26*(1-Supuestos!$B$3),0)) -> 1091 | M26: https://www.viator.com/es-MX/tours/Mexico-City/x/d628-5596307P2
A27: Andrea — Artistic and Cultural Tour in Tepito | B27: Artistic and Cultural Tour in Tepito | C27: Centro Histórico | D27: Airbnb Experiences | F27: 0 | G27: 870 | H27: =IF(G27="","",ROUND(G27*(1-Supuestos!$B$3),0)) -> 609 | M27: https://www.airbnb.com/experiences/6916169
A28: Andrés (Pintando la Revolución) | B28: Painting the Revolution: Murals, Markets, and Pulque | C28: Centro Histórico | D28: Airbnb Experiences | F28: 0 | G28: 666 | H28: =IF(G28="","",ROUND(G28*(1-Supuestos!$B$3),0)) -> 466 | M28: https://www.airbnb.com/experiences/7051320
A29: Andrés (Pintando la Revolución) | B29: Pintando la revolución Muralismo y pulque en CDMX | C29: Centro Histórico | D29: Viator | F29: 0 | G29: 700 | H29: =IF(G29="","",ROUND(G29*(1-Supuestos!$B$3),0)) -> 490 | M29: https://www.viator.com/es-MX/tours/Mexico-City/x/d628-5580793P4
A30: Andrés (Pintando la Revolución) | B30: Santa María la Rivera librería flotante, murales y pulque | C30: Centro Histórico | D30: Viator | F30: 0 | G30: 600 | H30: =IF(G30="","",ROUND(G30*(1-Supuestos!$B$3),0)) -> 420 | M30: https://www.viator.com/es-MX/tours/Mexico-City/x/d628-5580793P6
A31: Angel — A Food Tour of Historic Santa Maria la Ribera | B31: A Food Tour of Historic Santa Maria la Ribera | C31: Centro Histórico | D31: Airbnb Experiences | E31: 5 | F31: 16 | G31: 1314 | H31: =IF(G31="","",ROUND(G31*(1-Supuestos!$B$3),0)) -> 920 | M31: https://www.airbnb.com/experiences/6534668
A32: Angela Pilar — Mexico City Revealed Food and Culture Experience | B32: Mexico City Revealed Food and Culture Experience | C32: Centro Histórico | D32: Airbnb Experiences | F32: 0 | G32: 870 | H32: =IF(G32="","",ROUND(G32*(1-Supuestos!$B$3),0)) -> 609 | M32: https://www.airbnb.com/experiences/7117952
A33: Antonio — Trace mariachi legends in Garibaldi | B33: Trace mariachi legends in Garibaldi | C33: Centro Histórico | D33: Airbnb Experiences | F33: 0 | G33: 1628 | H33: =IF(G33="","",ROUND(G33*(1-Supuestos!$B$3),0)) -> 1140 | M33: https://www.airbnb.com/experiences/7252170
A34: Arc Tours | B34: Recorrido a Pie por el Templo Mayor y el Centro Histórico | C34: Centro Histórico | D34: Viator | F34: 0 | G34: 1200 | H34: =IF(G34="","",ROUND(G34*(1-Supuestos!$B$3),0)) -> 840 | M34: https://www.viator.com/es-MX/tours/Mexico-City/x/d628-484176P6
A35: Arte Para Todxs | B35: Diego Rivera & Bellas Artes: Mural Masterpieces | C35: Centro Histórico | D35: Airbnb Experiences | F35: 0 | G35: 1073 | H35: =IF(G35="","",ROUND(G35*(1-Supuestos!$B$3),0)) -> 751 | M35: https://www.airbnb.com/experiences/7224665
A36: Arte Para Todxs | B36: San Ildefonso: Where Muralism Began | C36: Centro Histórico | D36: Airbnb Experiences | F36: 0 | G36: 1073 | H36: =IF(G36="","",ROUND(G36*(1-Supuestos!$B$3),0)) -> 751 | M36: https://www.airbnb.com/experiences/7224702
A37: Artours CDMX | B37: Centro de la CDMX como Nunca lo Viste Historia y Secretos | C37: Centro Histórico | D37: Viator | E37: 5 | F37: 1 | G37: 1733 | H37: =IF(G37="","",ROUND(G37*(1-Supuestos!$B$3),0)) -> 1213 | M37: https://www.viator.com/es-MX/tours/Mexico-City/x/d628-5571656P3
A38: Aztec Action | B38: Ciudad de México: tour a pie por la historia del catolicismo con guía | C38: Centro Histórico | D38: GetYourGuide | F38: 0 | G38: 350 | H38: =IF(G38="","",ROUND(G38*(1-Supuestos!$B$3),0)) -> 245 | M38: https://www.getyourguide.com/es-mx/ciudad-de-mexico-l194/-t1362651/
A39: AztecAdvendTour | B39: Ciudad de México: Tour queer de comida y vida nocturna en Garibaldi y la calle Cuba | C39: Centro Histórico | D39: GetYourGuide | F39: 0 | G39: 2500 | H39: =IF(G39="","",ROUND(G39*(1-Supuestos!$B$3),0)) -> 1750 | M39: https://www.getyourguide.com/es-mx/ciudad-de-mexico-l194/-t1362189/
A40: AztecAdvendTour | B40: Crónicas del Centro: Historias Vivas de la Ciudad de México | C40: Centro Histórico | D40: GetYourGuide | E40: 5 | F40: 1 | G40: 980 | H40: =IF(G40="","",ROUND(G40*(1-Supuestos!$B$3),0)) -> 686 | M40: https://www.getyourguide.com/es-mx/ciudad-de-mexico-l194/-t1071997/
A41: Baika Rool | B41: Aventura en bici por el Centro Histórico de la Ciudad de México | C41: Centro Histórico | D41: Viator | E41: 5 | F41: 9 | G41: 700 | H41: =IF(G41="","",ROUND(G41*(1-Supuestos!$B$3),0)) -> 490 | J41: @baikarool | M41: https://www.viator.com/es-MX/tours/Mexico-City/x/d628-323040P4
A42: Beatriz — History and culture in Mexico City | B42: History and culture in Mexico City | C42: Centro Histórico | D42: Airbnb Experiences | E42: 5 | F42: 2 | G42: 925 | H42: =IF(G42="","",ROUND(G42*(1-Supuestos!$B$3),0)) -> 648 | M42: https://www.airbnb.com/experiences/6717908
A43: Bernardo — Taste CDMX with a culinary writer | B43: Taste CDMX with a culinary writer | C43: Centro Histórico | D43: Airbnb Experiences | E43: 5 | F43: 17 | G43: 1036 | H43: =IF(G43="","",ROUND(G43*(1-Supuestos!$B$3),0)) -> 725 | I43: https://gourmetdemexico.com.mx/gastronomia-mexicana/the-blind-taste-la-experiencia-gastronomica-secreta-de-john-bernardo/ | J43: @johnbernardomx | M43: https://www.airbnb.com/experiences/6199813
A44: BEST TOUR CDMX | B44: Mercados Mágicos de la Ciudad de México | C44: Centro Histórico | D44: Viator | E44: 4.8 | F44: 16 | G44: 1100 | H44: =IF(G44="","",ROUND(G44*(1-Supuestos!$B$3),0)) -> 770 | J44: @besttourcdmx | M44: https://www.viator.com/es-MX/tours/Mexico-City/x/d628-312155P2
A45: Bikes and Munchies | B45: Bike tour in Polanco's Art and Architecture | C45: Reforma/Juárez | D45: Airbnb Experiences | F45: 0 | G45: 1202 | H45: =IF(G45="","",ROUND(G45*(1-Supuestos!$B$3),0)) -> 841 | I45: https://www.bikesandmunchies.com/ | J45: @bikesandmunchies | L45: 525525356055 | M45: https://www.airbnb.com/experiences/7212087
A46: Bikes and Munchies | B46: Ciudad de México: tour en bicicleta por Roma y Condesa con comida callejera | C46: Bici · varias colonias | D46: GetYourGuide | E46: 5 | F46: 2 | G46: 1663.51 | H46: =IF(G46="","",ROUND(G46*(1-Supuestos!$B$3),0)) -> 1164 | I46: https://www.bikesandmunchies.com/ | J46: @bikesandmunchies | L46: 525525356055 | M46: https://www.getyourguide.com/es-mx/ciudad-de-mexico-l194/-t1037082/
A47: Bikes and Munchies | B47: Ciudad de México: tour en bicicleta por Roma y Condesa con comida callejera | C47: Bici · varias colonias | D47: Airbnb Experiences | E47: 4.95 | F47: 1633 | G47: 1572 | H47: =IF(G47="","",ROUND(G47*(1-Supuestos!$B$3),0)) -> 1100 | I47: https://www.bikesandmunchies.com/ | J47: @bikesandmunchies | L47: 525525356055 | M47: https://www.airbnb.com/experiences/102485
A48: Bikes and Munchies | B48: Cycle to Michelin tacos with food lovers | C48: Reforma/Juárez | D48: Airbnb Experiences | F48: 0 | G48: 1942 | H48: =IF(G48="","",ROUND(G48*(1-Supuestos!$B$3),0)) -> 1359 | I48: https://www.bikesandmunchies.com/ | J48: @bikesandmunchies | L48: 525525356055 | M48: https://www.airbnb.com/experiences/7211965
A49: Bikes and Munchies | B49: Tour de comida callejera con amigos | C49: Bici · varias colonias | D49: Viator | E49: 5 | F49: 334 | G49: 1750 | H49: =IF(G49="","",ROUND(G49*(1-Supuestos!$B$3),0)) -> 1225 | I49: https://www.bikesandmunchies.com/ | J49: @bikesandmunchies | L49: 525525356055 | M49: https://www.viator.com/es-MX/tours/Mexico-City/x/d628-227508P1
A50: Bikes and Munchies | B50: Tour Santa María la Rivera, Picados y Bicicletas | C50: Centro Histórico | D50: Viator | E50: 5 | F50: 10 | G50: 1435 | H50: =IF(G50="","",ROUND(G50*(1-Supuestos!$B$3),0)) -> 1004 | I50: https://www.bikesandmunchies.com/ | J50: @bikesandmunchies | L50: 525525356055 | M50: https://www.viator.com/es-MX/tours/Mexico-City/x/d628-227508P3
A51: Bikes and Munchies | B51: Tour Santa María la Rivera, Picados y Bicicletas | C51: Centro Histórico | D51: Airbnb Experiences | E51: 5 | F51: 32 | G51: 1258 | H51: =IF(G51="","",ROUND(G51*(1-Supuestos!$B$3),0)) -> 881 | I51: https://www.bikesandmunchies.com/ | J51: @bikesandmunchies | L51: 525525356055 | M51: https://www.airbnb.com/experiences/2705659
A52: Bondabu | B52: Recorrido profundo por La Merced y mercados emblemáticos de la Ciudad de México | C52: Centro Histórico | D52: Viator | E52: 4.9 | F52: 105 | G52: 2013 | H52: =IF(G52="","",ROUND(G52*(1-Supuestos!$B$3),0)) -> 1409 | I52: https://bondabu.com/ | J52: @bondabu_tours | K52: hola@bondabu.com | M52: https://www.viator.com/es-MX/tours/Mexico-City/x/d628-67901P2
A53: Bondabu | B53: Tour de comida callejera por la Ciudad de México | C53: Centro Histórico | D53: Viator | E53: 5 | F53: 14 | G53: 2188 | H53: =IF(G53="","",ROUND(G53*(1-Supuestos!$B$3),0)) -> 1532 | I53: https://bondabu.com/ | J53: @bondabu_tours | K53: hola@bondabu.com | M53: https://www.viator.com/es-MX/tours/Mexico-City/x/d628-67901P5
A54: Bondabu | B54: Tour de tacos por la calle de la Ciudad de México | C54: Centro Histórico | D54: Viator | E54: 4.7 | F54: 24 | G54: 2450 | H54: =IF(G54="","",ROUND(G54*(1-Supuestos!$B$3),0)) -> 1715 | I54: https://bondabu.com/ | J54: @bondabu_tours | K54: hola@bondabu.com | M54: https://www.viator.com/es-MX/tours/Mexico-City/x/d628-67901P3
A55: Camina la Ciudad | B55: Discover the history of the center | C55: Centro Histórico | D55: Airbnb Experiences | E55: 4.97 | F55: 1365 | G55: 740 | H55: =IF(G55="","",ROUND(G55*(1-Supuestos!$B$3),0)) -> 518 | J55: @caminalaciudad | M55: https://www.airbnb.com/experiences/647391
A56: Caminatas con Laura | B56: Tour Curioso y original en el Centro Histórico de la CDMX | C56: Centro Histórico | D56: Viator | E56: 5 | F56: 4 | G56: 700 | H56: =IF(G56="","",ROUND(G56*(1-Supuestos!$B$3),0)) -> 490 | M56: https://www.viator.com/es-MX/tours/Mexico-City/x/d628-483975P1
A57: Carlos San Roman | B57: Ciudad de México: tour guiado a pie por el patrimonio judío | C57: Centro Histórico | D57: GetYourGuide | E57: 5 | F57: 3 | G57: 6250 | H57: =IF(G57="","",ROUND(G57*(1-Supuestos!$B$3),0)) -> 4375 | M57: https://www.getyourguide.com/es-mx/ciudad-de-mexico-l194/-t1084837/
A58: Cecilia | B58: Tacos icónicos de El Centro guiados por Taco Crawl en CDMX | C58: Centro Histórico | D58: Viator | E58: 5 | F58: 4 | G58: 2100 | H58: =IF(G58="","",ROUND(G58*(1-Supuestos!$B$3),0)) -> 1470 | M58: https://www.viator.com/es-MX/tours/Mexico-City/x/d628-5597153P4
A59: Centro Histórico México. Tour Gourmet-Cultural | B59: Cultural y Gourmet tour Centro Histórico Mexico | C59: Centro Histórico | D59: Viator | F59: 0 | G59: 2328 | H59: =IF(G59="","",ROUND(G59*(1-Supuestos!$B$3),0)) -> 1630 | M59: https://www.viator.com/es-MX/tours/Mexico-City/x/d628-5664399P1
A60: Chaa' México | B60: CDMX: Descubre las joyas secretas de Chapultepec en bicicleta | C60: Bici · varias colonias | D60: GetYourGuide | E60: 5 | F60: 2 | G60: 1750 | H60: =IF(G60="","",ROUND(G60*(1-Supuestos!$B$3),0)) -> 1225 | M60: https://www.getyourguide.com/es-mx/ciudad-de-mexico-l194/-t1078314/
A61: Chaa' México | B61: CDMX: Descubre las joyas secretas de Chapultepec en bicicleta | C61: Bici · varias colonias | D61: Viator | F61: 0 | G61: 1400 | H61: =IF(G61="","",ROUND(G61*(1-Supuestos!$B$3),0)) -> 980 | M61: https://www.viator.com/es-MX/tours/Mexico-City/x/d628-5556552P1
A62: Charming Mexico | B62: Muralismo Mexicano Más Allá de Bellas Artes | C62: Centro Histórico | D62: Viator | F62: 0 | G62: 350 | H62: =IF(G62="","",ROUND(G62*(1-Supuestos!$B$3),0)) -> 245 | M62: https://www.viator.com/es-MX/tours/Mexico-City/x/d628-5613679P2
A63: Chez Mannu | B63: Ciudad de México: historia queer mexicana | C63: Centro Histórico | D63: GetYourGuide | E63: 4.86 | F63: 35 | G63: 414.4 | H63: =IF(G63="","",ROUND(G63*(1-Supuestos!$B$3),0)) -> 290 | J63: @chezmannu | M63: https://www.getyourguide.com/es-mx/ciudad-de-mexico-l194/-t690492/
A64: ChicVacay | B64: Ciudad de México: tour guiado por el Palacio de Bellas Artes | C64: Centro Histórico | D64: Viator | E64: 5 | F64: 9 | G64: 1050 | H64: =IF(G64="","",ROUND(G64*(1-Supuestos!$B$3),0)) -> 735 | M64: https://www.viator.com/es-MX/tours/Mexico-City/x/d628-428703P1
A65: ChicVacay | B65: Ciudad de México: tour guiado por el Palacio de Bellas Artes | C65: Centro Histórico | D65: GetYourGuide | E65: 5 | F65: 1 | G65: 1028.98 | H65: =IF(G65="","",ROUND(G65*(1-Supuestos!$B$3),0)) -> 720 | M65: https://www.getyourguide.com/es-mx/ciudad-de-mexico-l194/-t1227187/
A66: Chilanga Route on Wheels | B66: CDMX: recorrido en bicicleta, teleférico y Chapultepec oculto | C66: Bici · varias colonias | D66: GetYourGuide | E66: 4.85 | F66: 34 | G66: 850 | H66: =IF(G66="","",ROUND(G66*(1-Supuestos!$B$3),0)) -> 595 | M66: https://www.getyourguide.com/es-mx/ciudad-de-mexico-l194/-t1228414/
A67: Chilangadas Bike Tours | B67: Ciudad de México: excursión guiada en bici por la cultura y los sabores locales | C67: Bici · varias colonias | D67: GetYourGuide | E67: 5 | F67: 16 | G67: 1400 | H67: =IF(G67="","",ROUND(G67*(1-Supuestos!$B$3),0)) -> 980 | I67: https://www.chilangadastours.com/ | J67: @chilangadastourscdmx | M67: https://www.getyourguide.com/es-mx/ciudad-de-mexico-l194/-t1093680/
A68: Chilangadas Bike Tours | B68: Ciudad de México: excursión guiada en bici por la cultura y los sabores locales | C68: Bici · varias colonias | D68: Viator | E68: 5 | F68: 3 | G68: 1250 | H68: =IF(G68="","",ROUND(G68*(1-Supuestos!$B$3),0)) -> 875 | I68: https://www.chilangadastours.com/ | J68: @chilangadastourscdmx | M68: https://www.viator.com/es-MX/tours/Mexico-City/x/d628-5512428P2
A69: Chilango Insider | B69: Centro histórico de la Ciudad de México: tour a pie y joyas ocultas | C69: Centro Histórico | D69: GetYourGuide | E69: 5 | F69: 8 | G69: 1250 | H69: =IF(G69="","",ROUND(G69*(1-Supuestos!$B$3),0)) -> 875 | J69: @chilangoinsider | M69: https://www.getyourguide.com/es-mx/ciudad-de-mexico-l194/-t1244105/
A70: Chilangueando | B70: Centro histórico walking tour a través del tiempo y el espacio | C70: Centro Histórico | D70: Viator | E70: 5 | F70: 14 | G70: 660 | H70: =IF(G70="","",ROUND(G70*(1-Supuestos!$B$3),0)) -> 462 | M70: https://www.viator.com/es-MX/tours/Mexico-City/x/d628-421181P3
A71: Chilangueando | B71: Tour de Tacos e Historia en el Centro Histórico con Todo Incluido | C71: Centro Histórico | D71: Viator | E71: 4.9 | F71: 16 | G71: 1080 | H71: =IF(G71="","",ROUND(G71*(1-Supuestos!$B$3),0)) -> 756 | M71: https://www.viator.com/es-MX/tours/Mexico-City/x/d628-421181P4
A72: Chilantours | B72: Ciudad de México: callejón del Centro Histórico | C72: Centro Histórico | D72: Viator | F72: 0 | G72: 450 | H72: =IF(G72="","",ROUND(G72*(1-Supuestos!$B$3),0)) -> 315 | M72: https://www.viator.com/es-MX/tours/Mexico-City/x/d628-5623541P1
A73: Chilantours | B73: Ciudad de México: callejón del Centro Histórico | C73: Centro Histórico | D73: GetYourGuide | E73: 5 | F73: 3 | G73: 450 | H73: =IF(G73="","",ROUND(G73*(1-Supuestos!$B$3),0)) -> 315 | M73: https://www.getyourguide.com/es-mx/ciudad-de-mexico-l194/-t1335110/
A74: Chill N Go | B74: Exclusive Tour to Templo Mayor in CDMX | C74: Centro Histórico | D74: Airbnb Experiences | E74: 5 | F74: 4 | G74: 1202 | H74: =IF(G74="","",ROUND(G74*(1-Supuestos!$B$3),0)) -> 841 | I74: https://www.chillandgotours.com/ | J74: @chillandgotours | K74: carlos.castillo@chillandgotours.com | M74: https://www.airbnb.com/experiences/6101703
A75: Chill N Go | B75: TOUR EXCLUSIVO Catedral Metropolitana - Grupos pequeños | C75: Centro Histórico | D75: Viator | E75: 4.6 | F75: 10 | G75: 800 | H75: =IF(G75="","",ROUND(G75*(1-Supuestos!$B$3),0)) -> 560 | I75: https://www.chillandgotours.com/ | J75: @chillandgotours | K75: carlos.castillo@chillandgotours.com | M75: https://www.viator.com/es-MX/tours/Mexico-City/x/d628-289853P50
A76: Chill N Go | B76: TOUR EXCLUSIVO Catedral Metropolitana - Grupos pequeños | C76: Centro Histórico | D76: Airbnb Experiences | E76: 5 | F76: 1 | G76: 870 | H76: =IF(G76="","",ROUND(G76*(1-Supuestos!$B$3),0)) -> 609 | I76: https://www.chillandgotours.com/ | J76: @chillandgotours | K76: carlos.castillo@chillandgotours.com | M76: https://www.airbnb.com/experiences/6106182
A77: Chill N Go | B77: Visita guiada por el Palacio de Bellas Artes | C77: Centro Histórico | D77: Airbnb Experiences | E77: 5 | F77: 4 | G77: 1202 | H77: =IF(G77="","",ROUND(G77*(1-Supuestos!$B$3),0)) -> 841 | I77: https://www.chillandgotours.com/ | J77: @chillandgotours | K77: carlos.castillo@chillandgotours.com | M77: https://www.airbnb.com/experiences/6458982
A78: Chill N Go | B78: Visita guiada por el Palacio de Bellas Artes | C78: Centro Histórico | D78: Civitatis | E78: 4.85 | F78: 12 | G78: 5088 | H78: =IF(G78="","",ROUND(G78*(1-Supuestos!$B$3),0)) -> 3562 | I78: https://www.chillandgotours.com/ | J78: @chillandgotours | K78: carlos.castillo@chillandgotours.com | M78: https://www.civitatis.com/es/ciudad-de-mexico/visita-guiada-palacio-bellas-artes/
A79: Circuitos por Mexico | B79: Ciudad de México: tour nocturno por la Plaza Garibaldi con mariachis | C79: Centro Histórico | D79: GetYourGuide | F79: 0 | G79: 2242 | H79: =IF(G79="","",ROUND(G79*(1-Supuestos!$B$3),0)) -> 1569 | I79: https://www.circuitospormexico.com/ | J79: @circuitospormexico | K79: info@circuitospormexico.com | L79: 528115565847 | M79: https://www.getyourguide.com/es-mx/ciudad-de-mexico-l194/-t979538/
A80: City Art Tours | B80: Tour privado de muralismo en la Ciudad de México | C80: Centro Histórico | D80: Viator | E80: 4.9 | F80: 14 | G80: 1181 | H80: =IF(G80="","",ROUND(G80*(1-Supuestos!$B$3),0)) -> 827 | I80: http://cityarttoursmexico.com/ | J80: @cityarttours | K80: info.cityarttours@gmail.com | L80: 529982122972 | M80: https://www.viator.com/es-MX/tours/Mexico-City/x/d628-125512P124
A81: City Unscripted | B81: Tour de tacos en la Ciudad de México con un entusiasta local: 100% personalizado y privado | C81: Centro Histórico | D81: Viator | E81: 4.8 | F81: 31 | G81: 2433 | H81: =IF(G81="","",ROUND(G81*(1-Supuestos!$B$3),0)) -> 1703 | I81: https://www.cityunscripted.com/ | J81: @cityunscripted | K81: info@cityunscripted.com | M81: https://www.viator.com/es-MX/tours/Mexico-City/x/d628-30791P610
A82: City Unscripted | B82: Tours gastronómicos privados personalizados en la Ciudad de México con un guía local | C82: Centro Histórico | D82: Viator | E82: 5 | F82: 11 | G82: 3189 | H82: =IF(G82="","",ROUND(G82*(1-Supuestos!$B$3),0)) -> 2232 | I82: https://www.cityunscripted.com/ | J82: @cityunscripted | K82: info@cityunscripted.com | M82: https://www.viator.com/es-MX/tours/Mexico-City/x/d628-30791P275
A83: Claudia Bárcena (not.lost.cdmx) | B83: CDMX on Two Wheels: Hidden Gems Ride | C83: Bici · varias colonias | D83: Airbnb Experiences | F83: 0 | G83: 1314 | H83: =IF(G83="","",ROUND(G83*(1-Supuestos!$B$3),0)) -> 920 | M83: https://www.airbnb.com/experiences/6487196
A84: Claudia Bárcena (not.lost.cdmx) | B84: Paseo en bicicleta al amanecer por el Parque de Chapultepec y Cablebús | C84: Bici · varias colonias | D84: Viator | E84: 5 | F84: 1 | G84: 950 | H84: =IF(G84="","",ROUND(G84*(1-Supuestos!$B$3),0)) -> 665 | M84: https://www.viator.com/es-MX/tours/Mexico-City/x/d628-5659536P4
A85: Claudia Bárcena (not.lost.cdmx) | B85: Paseo en bicicleta al amanecer por el Parque de Chapultepec y Cablebús | C85: Bici · varias colonias | D85: GetYourGuide | F85: 0 | G85: 784 | H85: =IF(G85="","",ROUND(G85*(1-Supuestos!$B$3),0)) -> 549 | M85: https://www.getyourguide.com/es-mx/ciudad-de-mexico-l194/-t1426003/
A86: Claudia Bárcena (not.lost.cdmx) | B86: Paseo en bicicleta al amanecer por el Parque de Chapultepec y Cablebús | C86: Bici · varias colonias | D86: Airbnb Experiences | F86: 0 | G86: 1073 | H86: =IF(G86="","",ROUND(G86*(1-Supuestos!$B$3),0)) -> 751 | M86: https://www.airbnb.com/experiences/6637244
A87: Claudia Bárcena (not.lost.cdmx) | B87: Paseo en bicicleta por la Ciudad de México | C87: Bici · varias colonias | D87: Viator | E87: 5 | F87: 1 | G87: 800 | H87: =IF(G87="","",ROUND(G87*(1-Supuestos!$B$3),0)) -> 560 | M87: https://www.viator.com/es-MX/tours/Mexico-City/x/d628-5497606P2
A88: Claudia Bárcena (not.lost.cdmx) | B88: Tour en bicicleta, tacos y teleférico en Ciudad de México | C88: Bici · varias colonias | D88: Viator | E88: 5 | F88: 4 | G88: 980 | H88: =IF(G88="","",ROUND(G88*(1-Supuestos!$B$3),0)) -> 686 | M88: https://www.viator.com/es-MX/tours/Mexico-City/x/d628-5497606P3
A89: Claudia Bárcena (not.lost.cdmx) | B89: Tour gastronómico local a pie CDMX | C89: Centro Histórico | D89: Viator | F89: 0 | G89: 980 | H89: =IF(G89="","",ROUND(G89*(1-Supuestos!$B$3),0)) -> 686 | M89: https://www.viator.com/es-MX/tours/Mexico-City/x/d628-5659536P5
A90: Context Travel | B90: Small-group Zócalo walking tour in Mexico City | C90: Centro Histórico | D90: Airbnb Experiences | F90: 0 | G90: 2090 | H90: =IF(G90="","",ROUND(G90*(1-Supuestos!$B$3),0)) -> 1463 | I90: https://www.contexttravel.com/ | J90: @contexttravel | M90: https://www.airbnb.com/experiences/6101365
A91: Corazón Histórico | B91: Ciudad de México: recorrido completo por el centro histórico | C91: Centro Histórico | D91: Viator | E91: 4.4 | F91: 13 | G91: 1225 | H91: =IF(G91="","",ROUND(G91*(1-Supuestos!$B$3),0)) -> 858 | M91: https://www.viator.com/es-MX/tours/Mexico-City/x/d628-206432P9
A92: Corazón Histórico | B92: Ciudad de México: recorrido completo por el centro histórico | C92: Centro Histórico | D92: GetYourGuide | F92: 0 | G92: 4500 | H92: =IF(G92="","",ROUND(G92*(1-Supuestos!$B$3),0)) -> 3150 | M92: https://www.getyourguide.com/es-mx/ciudad-de-mexico-l194/-t607878/
A93: Culinary Backstreets | B93: 2026 Secretos Gastronómicos del Centro Histórico | C93: Centro Histórico | D93: Viator | E93: 5 | F93: 11 | G93: 2450 | H93: =IF(G93="","",ROUND(G93*(1-Supuestos!$B$3),0)) -> 1715 | I93: https://culinarybackstreets.com/city-guides/mexico-city | J93: @culinarybackstreets | M93: https://www.viator.com/es-MX/tours/Mexico-City/x/d628-5589711P22
A94: Curado Tours | B94: Tour de cantinas y taquerias por Ciudad de Mexico | C94: Centro Histórico | D94: Civitatis | E94: 5 | F94: 4 | G94: 9361 | H94: =IF(G94="","",ROUND(G94*(1-Supuestos!$B$3),0)) -> 6553 | I94: https://curadotours19.wixsite.com/misitio | J94: @curadotours19 | K94: curadotours19@gmail.com | L94: 525579271080 | M94: https://www.civitatis.com/es/ciudad-de-mexico/tour-cantinas-bares-ciudad-mexico/
A95: Curiosidad Urbana | B95: Tour Histórico de Ciudad de México Perspectiva Local | C95: Centro Histórico | D95: Viator | F95: 0 | G95: 300 | H95: =IF(G95="","",ROUND(G95*(1-Supuestos!$B$3),0)) -> 210 | M95: https://www.viator.com/es-MX/tours/Mexico-City/x/d628-5655578P1
A96: Daniela — No boring history & Mexican food with a local | B96: No boring history & Mexican food with a local | C96: Centro Histórico | D96: Airbnb Experiences | E96: 5 | F96: 51 | G96: 1147 | H96: =IF(G96="","",ROUND(G96*(1-Supuestos!$B$3),0)) -> 803 | M96: https://www.airbnb.com/experiences/4083230
A97: Daniela Fernanda Gaeta González | B97: Tour por la Catedral y el Templo Mayor Murales de Diego Rivera | C97: Centro Histórico | D97: Civitatis | E97: 5 | F97: 1 | G97: 3006 | H97: =IF(G97="","",ROUND(G97*(1-Supuestos!$B$3),0)) -> 2104 | K97: tiapanitours@gmail.com | M97: https://www.civitatis.com/es/ciudad-de-mexico/tour-catedral-templo-mayor-murales/
A98: Daniella — Tour the Palace of Fine Arts with an Art Histori | B98: Tour the Palace of Fine Arts with an Art Historian | C98: Centro Histórico | D98: Airbnb Experiences | F98: 0 | G98: 1054 | H98: =IF(G98="","",ROUND(G98*(1-Supuestos!$B$3),0)) -> 738 | M98: https://www.airbnb.com/experiences/7285807
A99: David — A walk through the city's oldest neighborhood | B99: A walk through the city's oldest neighborhood | C99: Centro Histórico | D99: Airbnb Experiences | E99: 5 | F99: 22 | G99: 3256 | H99: =IF(G99="","",ROUND(G99*(1-Supuestos!$B$3),0)) -> 2279 | M99: https://www.airbnb.com/experiences/267718
A100: David Jose — Spiritual Routes: Tlatelolco, Sonora and Tepito | B100: Spiritual Routes: Tlatelolco, Sonora and Tepito | C100: Centro Histórico | D100: Airbnb Experiences | E100: 5 | F100: 1 | G100: 870 | H100: =IF(G100="","",ROUND(G100*(1-Supuestos!$B$3),0)) -> 609 | M100: https://www.airbnb.com/experiences/6866178
...

Sheet Por plataforma
A1: Plataforma | B1: Anuncios | C1: PVP promedio (MXN) | D1: Neto promedio (MXN)
A2: Airbnb Experiences | B2: =COUNTIF(Netos!$D:$D,A2) -> 136 | C2: =ROUND(AVERAGEIF(Netos!$D$2:$D$456,A2,Netos!$G$2:$G$456),0) -> 1203 | D2: =ROUND(AVERAGEIF(Netos!$D$2:$D$456,A2,Netos!$H$2:$H$456),0) -> 842
A3: Civitatis | B3: =COUNTIF(Netos!$D:$D,A3) -> 23 | C3: =ROUND(AVERAGEIF(Netos!$D$2:$D$456,A3,Netos!$G$2:$G$456),0) -> 2444 | D3: =ROUND(AVERAGEIF(Netos!$D$2:$D$456,A3,Netos!$H$2:$H$456),0) -> 1711
A4: GetYourGuide | B4: =COUNTIF(Netos!$D:$D,A4) -> 116 | C4: =ROUND(AVERAGEIF(Netos!$D$2:$D$456,A4,Netos!$G$2:$G$456),0) -> 2075 | D4: =ROUND(AVERAGEIF(Netos!$D$2:$D$456,A4,Netos!$H$2:$H$456),0) -> 1453
A5: Viator | B5: =COUNTIF(Netos!$D:$D,A5) -> 180 | C5: =ROUND(AVERAGEIF(Netos!$D$2:$D$456,A5,Netos!$G$2:$G$456),0) -> 1482 | D5: =ROUND(AVERAGEIF(Netos!$D$2:$D$456,A5,Netos!$H$2:$H$456),0) -> 1038
